asciietch/__init__.py
asciietch/graph.py
asciietch-1.0.6.dist-info/AUTHORS.md
asciietch-1.0.6.dist-info/LICENSE
asciietch-1.0.6.dist-info/METADATA
asciietch-1.0.6.dist-info/NOTICE
asciietch-1.0.6.dist-info/WHEEL
asciietch-1.0.6.dist-info/top_level.txt
asciietch-1.0.6.dist-info/RECORD
