Metadata-Version: 2.1
Name: asciietch
Version: 1.0.6
Summary: A library for graphing charts using ascii characters.
Home-page: https://github.com/linkedin/asciietch
Author: Steven R. Callister
License: License :: OSI Approved :: BSD License
Platform: UNKNOWN
Classifier: Development Status :: 5 - Production/Stable
Classifier: Environment :: Console
Classifier: Intended Audience :: Developers
Classifier: Intended Audience :: Information Technology
Classifier: Intended Audience :: System Administrators
Classifier: License :: OSI Approved :: BSD License
Classifier: Programming Language :: Python :: 3.6
Classifier: Programming Language :: Python :: 3 :: Only
Classifier: Operating System :: POSIX :: Linux
Requires-Dist: parsedatetime (==2.4)
Requires-Dist: setuptools (>=30)
